setup.cfg
setup.py
rabbitmq_statsd_bridge/__init__.py
rabbitmq_statsd_bridge/rabbitmq_statsd_bridge.py
rabbitmq_statsd_bridge.egg-info/PKG-INFO
rabbitmq_statsd_bridge.egg-info/SOURCES.txt
rabbitmq_statsd_bridge.egg-info/dependency_links.txt
rabbitmq_statsd_bridge.egg-info/requires.txt
rabbitmq_statsd_bridge.egg-info/top_level.txt