Metadata-Version: 1.0
Name: rabbitmq-statsd-bridge
Version: 0.1a1
Summary: Populate statsd from rabbitmq
Home-page: FIXME
Author: David Honour
Author-email: david@foolswood.co.uk
License: GPL3
Platform: UNKNOWN
